aceso/__init__.py
aceso/decay.py
aceso/gravity.py
aceso-0.1.0.dist-info/DESCRIPTION.rst
aceso-0.1.0.dist-info/METADATA
aceso-0.1.0.dist-info/RECORD
aceso-0.1.0.dist-info/WHEEL
aceso-0.1.0.dist-info/metadata.json
aceso-0.1.0.dist-info/top_level.txt
