Metadata-Version: 2.0
Name: aceso
Version: 0.1.0
Summary: Lightweight package to calculate 2SFCA and other measures of spatial accessibility
Home-page: http://github.com/tetraptych/aceso
Author: Brian Lewis
Author-email: brianburkelewis@gmail.com
License: MIT
Keywords: geospatial,geo,gis,2SFCA,gravity,access,catchment-area
Platform: UNKNOWN
Classifier: Intended Audience :: Developers
Classifier: Intended Audience :: Science/Research
Classifier: Programming Language :: Python :: 2.7
Classifier: Programming Language :: Python :: 3.5
Classifier: Programming Language :: Python :: 3.6
Classifier: Topic :: Scientific/Engineering :: GIS
Requires-Python: >=2.7
Requires-Dist: numpy (>=1.11.0)
